Metadata-Version: 2.1
Name: first-package-Ionel-Ujica
Version: 0.2.0
Summary: My first package
Author: Ionel
Author-email: ionelujica@yahoo.com
